.hgignore
.project
.pydevproject
LICENSE
MANIFEST.in
README.txt
bootstrap.py
buildout.cfg
setup.py
bin/buildout
docs/HISTORY.txt
docs/README.txt
src/ztfy/__init__.py
src/ztfy.extfile.egg-info/PKG-INFO
src/ztfy.extfile.egg-info/SOURCES.txt
src/ztfy.extfile.egg-info/dependency_links.txt
src/ztfy.extfile.egg-info/entry_points.txt
src/ztfy.extfile.egg-info/namespace_packages.txt
src/ztfy.extfile.egg-info/not-zip-safe
src/ztfy.extfile.egg-info/requires.txt
src/ztfy.extfile.egg-info/top_level.txt
src/ztfy/extfile/README.txt
src/ztfy/extfile/__init__.py
src/ztfy/extfile/blob.py
src/ztfy/extfile/configure.zcml
src/ztfy/extfile/database.py
src/ztfy/extfile/events.py
src/ztfy/extfile/extfile.py
src/ztfy/extfile/interfaces.py
src/ztfy/extfile/meta.zcml
src/ztfy/extfile/doctests/README.txt
src/ztfy/extfile/handler/__init__.py
src/ztfy/extfile/handler/interfaces.py
src/ztfy/extfile/handler/local/__init__.py
src/ztfy/extfile/handler/local/configure.zcml
src/ztfy/extfile/handler/local/interfaces.py
src/ztfy/extfile/handler/local/meta.zcml
src/ztfy/extfile/handler/local/metaconfigure.py
src/ztfy/extfile/handler/sftp/__init__.py
src/ztfy/extfile/handler/sftp/configure.zcml
src/ztfy/extfile/handler/sftp/interfaces.py
src/ztfy/extfile/handler/sftp/meta.zcml
src/ztfy/extfile/handler/sftp/metaconfigure.py
src/ztfy/extfile/locales/ztfy.extfile.pot
src/ztfy/extfile/locales/en/LC_MESSAGES/ztfy.extfile.mo
src/ztfy/extfile/locales/en/LC_MESSAGES/ztfy.extfile.po
src/ztfy/extfile/locales/fr/LC_MESSAGES/ztfy.extfile.mo
src/ztfy/extfile/locales/fr/LC_MESSAGES/ztfy.extfile.po
src/ztfy/extfile/namechooser/__init__.py
src/ztfy/extfile/namechooser/chooser.py
src/ztfy/extfile/namechooser/config.py
src/ztfy/extfile/namechooser/configure.zcml
src/ztfy/extfile/namechooser/interfaces.py
src/ztfy/extfile/namechooser/meta.zcml
src/ztfy/extfile/namechooser/metaconfigure.py
src/ztfy/extfile/tests/__init__.py
src/ztfy/extfile/tests/test_extfiledocs.py
src/ztfy/extfile/tests/test_extfiledocstrings.py